wexample_wex_addon_dev_javascript-0.0.57.dist-info/METADATA
wexample_wex_addon_dev_javascript-0.0.57.dist-info/WHEEL
wexample_wex_addon_dev_javascript-0.0.57.dist-info/entry_points.txt
wexample_wex_addon_dev_javascript/__init__.py
wexample_wex_addon_dev_javascript/__pycache__/__init__.py
wexample_wex_addon_dev_javascript/config_value/__init__.py
wexample_wex_addon_dev_javascript/config_value/javascript_package_readme_config_value.py
wexample_wex_addon_dev_javascript/file/__init__.py
wexample_wex_addon_dev_javascript/file/javascript_package_json_file.py
wexample_wex_addon_dev_javascript/javascript_addon_manager.py
wexample_wex_addon_dev_javascript/py.typed
wexample_wex_addon_dev_javascript/workdir/__init__.py
wexample_wex_addon_dev_javascript/workdir/javascript_package_workdir.py
wexample_wex_addon_dev_javascript/workdir/javascript_packages_suite_workdir.py
wexample_wex_addon_dev_javascript/workdir/javascript_workdir.py
wexample_wex_addon_dev_javascript-0.0.57.dist-info/RECORD
